{ "frames": [
   {
    "filename": "TDS 0.aseprite",
    "frame": { "x": 0, "y": 0, "w": 128, "h": 128 },
    "rotated": false,
    "trimmed": false,
    "spriteSourceSize": { "x": 0, "y": 0, "w": 128, "h": 128 },
    "sourceSize": { "w": 128, "h": 128 },
    "duration": 20
   },
   {
    "filename": "TDS 1.aseprite",
    "frame": { "x": 128, "y": 0, "w": 128, "h": 128 },
    "rotated": false,
    "trimmed": false,
    "spriteSourceSize": { "x": 0, "y": 0, "w": 128, "h": 128 },
    "sourceSize": { "w": 128, "h": 128 },
    "duration": 20
   },
   {
    "filename": "TDS 2.aseprite",
    "frame": { "x": 256, "y": 0, "w": 128, "h": 128 },
    "rotated": false,
    "trimmed": false,
    "spriteSourceSize": { "x": 0, "y": 0, "w": 128, "h": 128 },
    "sourceSize": { "w": 128, "h": 128 },
    "duration": 20
   },
   {
    "filename": "TDS 3.aseprite",
    "frame": { "x": 384, "y": 0, "w": 128, "h": 128 },
    "rotated": false,
    "trimmed": false,
    "spriteSourceSize": { "x": 0, "y": 0, "w": 128, "h": 128 },
    "sourceSize": { "w": 128, "h": 128 },
    "duration": 20
   },
   {
    "filename": "TDS 4.aseprite",
    "frame": { "x": 512, "y": 0, "w": 128, "h": 128 },
    "rotated": false,
    "trimmed": false,
    "spriteSourceSize": { "x": 0, "y": 0, "w": 128, "h": 128 },
    "sourceSize": { "w": 128, "h": 128 },
    "duration": 20
   },
   {
    "filename": "TDS 5.aseprite",
    "frame": { "x": 640, "y": 0, "w": 128, "h": 128 },
    "rotated": false,
    "trimmed": false,
    "spriteSourceSize": { "x": 0, "y": 0, "w": 128, "h": 128 },
    "sourceSize": { "w": 128, "h": 128 },
    "duration": 20
   },
   {
    "filename": "TDS 6.aseprite",
    "frame": { "x": 768, "y": 0, "w": 128, "h": 128 },
    "rotated": false,
    "trimmed": false,
    "spriteSourceSize": { "x": 0, "y": 0, "w": 128, "h": 128 },
    "sourceSize": { "w": 128, "h": 128 },
    "duration": 20
   },
   {
    "filename": "TDS 7.aseprite",
    "frame": { "x": 896, "y": 0, "w": 128, "h": 128 },
    "rotated": false,
    "trimmed": false,
    "spriteSourceSize": { "x": 0, "y": 0, "w": 128, "h": 128 },
    "sourceSize": { "w": 128, "h": 128 },
    "duration": 20
   },
   {
    "filename": "TDS 8.aseprite",
    "frame": { "x": 1024, "y": 0, "w": 128, "h": 128 },
    "rotated": false,
    "trimmed": false,
    "spriteSourceSize": { "x": 0, "y": 0, "w": 128, "h": 128 },
    "sourceSize": { "w": 128, "h": 128 },
    "duration": 20
   },
   {
    "filename": "TDS 9.aseprite",
    "frame": { "x": 1152, "y": 0, "w": 128, "h": 128 },
    "rotated": false,
    "trimmed": false,
    "spriteSourceSize": { "x": 0, "y": 0, "w": 128, "h": 128 },
    "sourceSize": { "w": 128, "h": 128 },
    "duration": 20
   },
   {
    "filename": "TDS 10.aseprite",
    "frame": { "x": 1280, "y": 0, "w": 128, "h": 128 },
    "rotated": false,
    "trimmed": false,
    "spriteSourceSize": { "x": 0, "y": 0, "w": 128, "h": 128 },
    "sourceSize": { "w": 128, "h": 128 },
    "duration": 20
   },
   {
    "filename": "TDS 11.aseprite",
    "frame": { "x": 1408, "y": 0, "w": 128, "h": 128 },
    "rotated": false,
    "trimmed": false,
    "spriteSourceSize": { "x": 0, "y": 0, "w": 128, "h": 128 },
    "sourceSize": { "w": 128, "h": 128 },
    "duration": 20
   },
   {
    "filename": "TDS 12.aseprite",
    "frame": { "x": 1536, "y": 0, "w": 128, "h": 128 },
    "rotated": false,
    "trimmed": false,
    "spriteSourceSize": { "x": 0, "y": 0, "w": 128, "h": 128 },
    "sourceSize": { "w": 128, "h": 128 },
    "duration": 20
   },
   {
    "filename": "TDS 13.aseprite",
    "frame": { "x": 1664, "y": 0, "w": 128, "h": 128 },
    "rotated": false,
    "trimmed": false,
    "spriteSourceSize": { "x": 0, "y": 0, "w": 128, "h": 128 },
    "sourceSize": { "w": 128, "h": 128 },
    "duration": 20
   },
   {
    "filename": "TDS 14.aseprite",
    "frame": { "x": 1792, "y": 0, "w": 128, "h": 128 },
    "rotated": false,
    "trimmed": false,
    "spriteSourceSize": { "x": 0, "y": 0, "w": 128, "h": 128 },
    "sourceSize": { "w": 128, "h": 128 },
    "duration": 20
   },
   {
    "filename": "TDS 15.aseprite",
    "frame": { "x": 1920, "y": 0, "w": 128, "h": 128 },
    "rotated": false,
    "trimmed": false,
    "spriteSourceSize": { "x": 0, "y": 0, "w": 128, "h": 128 },
    "sourceSize": { "w": 128, "h": 128 },
    "duration": 20
   },
   {
    "filename": "TDS 16.aseprite",
    "frame": { "x": 2048, "y": 0, "w": 128, "h": 128 },
    "rotated": false,
    "trimmed": false,
    "spriteSourceSize": { "x": 0, "y": 0, "w": 128, "h": 128 },
    "sourceSize": { "w": 128, "h": 128 },
    "duration": 20
   },
   {
    "filename": "TDS 17.aseprite",
    "frame": { "x": 2176, "y": 0, "w": 128, "h": 128 },
    "rotated": false,
    "trimmed": false,
    "spriteSourceSize": { "x": 0, "y": 0, "w": 128, "h": 128 },
    "sourceSize": { "w": 128, "h": 128 },
    "duration": 20
   },
   {
    "filename": "TDS 18.aseprite",
    "frame": { "x": 2304, "y": 0, "w": 128, "h": 128 },
    "rotated": false,
    "trimmed": false,
    "spriteSourceSize": { "x": 0, "y": 0, "w": 128, "h": 128 },
    "sourceSize": { "w": 128, "h": 128 },
    "duration": 20
   },
   {
    "filename": "TDS 19.aseprite",
    "frame": { "x": 2432, "y": 0, "w": 128, "h": 128 },
    "rotated": false,
    "trimmed": false,
    "spriteSourceSize": { "x": 0, "y": 0, "w": 128, "h": 128 },
    "sourceSize": { "w": 128, "h": 128 },
    "duration": 20
   },
   {
    "filename": "TDS 20.aseprite",
    "frame": { "x": 2560, "y": 0, "w": 128, "h": 128 },
    "rotated": false,
    "trimmed": false,
    "spriteSourceSize": { "x": 0, "y": 0, "w": 128, "h": 128 },
    "sourceSize": { "w": 128, "h": 128 },
    "duration": 20
   },
   {
    "filename": "TDS 21.aseprite",
    "frame": { "x": 2688, "y": 0, "w": 128, "h": 128 },
    "rotated": false,
    "trimmed": false,
    "spriteSourceSize": { "x": 0, "y": 0, "w": 128, "h": 128 },
    "sourceSize": { "w": 128, "h": 128 },
    "duration": 20
   },
   {
    "filename": "TDS 22.aseprite",
    "frame": { "x": 2816, "y": 0, "w": 128, "h": 128 },
    "rotated": false,
    "trimmed": false,
    "spriteSourceSize": { "x": 0, "y": 0, "w": 128, "h": 128 },
    "sourceSize": { "w": 128, "h": 128 },
    "duration": 20
   },
   {
    "filename": "TDS 23.aseprite",
    "frame": { "x": 2944, "y": 0, "w": 128, "h": 128 },
    "rotated": false,
    "trimmed": false,
    "spriteSourceSize": { "x": 0, "y": 0, "w": 128, "h": 128 },
    "sourceSize": { "w": 128, "h": 128 },
    "duration": 20
   },
   {
    "filename": "TDS 24.aseprite",
    "frame": { "x": 3072, "y": 0, "w": 128, "h": 128 },
    "rotated": false,
    "trimmed": false,
    "spriteSourceSize": { "x": 0, "y": 0, "w": 128, "h": 128 },
    "sourceSize": { "w": 128, "h": 128 },
    "duration": 20
   },
   {
    "filename": "TDS 25.aseprite",
    "frame": { "x": 3200, "y": 0, "w": 128, "h": 128 },
    "rotated": false,
    "trimmed": false,
    "spriteSourceSize": { "x": 0, "y": 0, "w": 128, "h": 128 },
    "sourceSize": { "w": 128, "h": 128 },
    "duration": 20
   },
   {
    "filename": "TDS 26.aseprite",
    "frame": { "x": 3328, "y": 0, "w": 128, "h": 128 },
    "rotated": false,
    "trimmed": false,
    "spriteSourceSize": { "x": 0, "y": 0, "w": 128, "h": 128 },
    "sourceSize": { "w": 128, "h": 128 },
    "duration": 20
   },
   {
    "filename": "TDS 27.aseprite",
    "frame": { "x": 3456, "y": 0, "w": 128, "h": 128 },
    "rotated": false,
    "trimmed": false,
    "spriteSourceSize": { "x": 0, "y": 0, "w": 128, "h": 128 },
    "sourceSize": { "w": 128, "h": 128 },
    "duration": 20
   },
   {
    "filename": "TDS 28.aseprite",
    "frame": { "x": 3584, "y": 0, "w": 128, "h": 128 },
    "rotated": false,
    "trimmed": false,
    "spriteSourceSize": { "x": 0, "y": 0, "w": 128, "h": 128 },
    "sourceSize": { "w": 128, "h": 128 },
    "duration": 20
   },
   {
    "filename": "TDS 29.aseprite",
    "frame": { "x": 3712, "y": 0, "w": 128, "h": 128 },
    "rotated": false,
    "trimmed": false,
    "spriteSourceSize": { "x": 0, "y": 0, "w": 128, "h": 128 },
    "sourceSize": { "w": 128, "h": 128 },
    "duration": 20
   },
   {
    "filename": "TDS 30.aseprite",
    "frame": { "x": 3840, "y": 0, "w": 128, "h": 128 },
    "rotated": false,
    "trimmed": false,
    "spriteSourceSize": { "x": 0, "y": 0, "w": 128, "h": 128 },
    "sourceSize": { "w": 128, "h": 128 },
    "duration": 20
   },
   {
    "filename": "TDS 31.aseprite",
    "frame": { "x": 3968, "y": 0, "w": 128, "h": 128 },
    "rotated": false,
    "trimmed": false,
    "spriteSourceSize": { "x": 0, "y": 0, "w": 128, "h": 128 },
    "sourceSize": { "w": 128, "h": 128 },
    "duration": 20
   },
   {
    "filename": "TDS 32.aseprite",
    "frame": { "x": 4096, "y": 0, "w": 128, "h": 128 },
    "rotated": false,
    "trimmed": false,
    "spriteSourceSize": { "x": 0, "y": 0, "w": 128, "h": 128 },
    "sourceSize": { "w": 128, "h": 128 },
    "duration": 20
   },
   {
    "filename": "TDS 33.aseprite",
    "frame": { "x": 4224, "y": 0, "w": 128, "h": 128 },
    "rotated": false,
    "trimmed": false,
    "spriteSourceSize": { "x": 0, "y": 0, "w": 128, "h": 128 },
    "sourceSize": { "w": 128, "h": 128 },
    "duration": 20
   },
   {
    "filename": "TDS 34.aseprite",
    "frame": { "x": 4352, "y": 0, "w": 128, "h": 128 },
    "rotated": false,
    "trimmed": false,
    "spriteSourceSize": { "x": 0, "y": 0, "w": 128, "h": 128 },
    "sourceSize": { "w": 128, "h": 128 },
    "duration": 20
   },
   {
    "filename": "TDS 35.aseprite",
    "frame": { "x": 4480, "y": 0, "w": 128, "h": 128 },
    "rotated": false,
    "trimmed": false,
    "spriteSourceSize": { "x": 0, "y": 0, "w": 128, "h": 128 },
    "sourceSize": { "w": 128, "h": 128 },
    "duration": 20
   },
   {
    "filename": "TDS 36.aseprite",
    "frame": { "x": 4608, "y": 0, "w": 128, "h": 128 },
    "rotated": false,
    "trimmed": false,
    "spriteSourceSize": { "x": 0, "y": 0, "w": 128, "h": 128 },
    "sourceSize": { "w": 128, "h": 128 },
    "duration": 20
   },
   {
    "filename": "TDS 37.aseprite",
    "frame": { "x": 4736, "y": 0, "w": 128, "h": 128 },
    "rotated": false,
    "trimmed": false,
    "spriteSourceSize": { "x": 0, "y": 0, "w": 128, "h": 128 },
    "sourceSize": { "w": 128, "h": 128 },
    "duration": 20
   },
   {
    "filename": "TDS 38.aseprite",
    "frame": { "x": 4864, "y": 0, "w": 128, "h": 128 },
    "rotated": false,
    "trimmed": false,
    "spriteSourceSize": { "x": 0, "y": 0, "w": 128, "h": 128 },
    "sourceSize": { "w": 128, "h": 128 },
    "duration": 20
   },
   {
    "filename": "TDS 39.aseprite",
    "frame": { "x": 4992, "y": 0, "w": 128, "h": 128 },
    "rotated": false,
    "trimmed": false,
    "spriteSourceSize": { "x": 0, "y": 0, "w": 128, "h": 128 },
    "sourceSize": { "w": 128, "h": 128 },
    "duration": 20
   },
   {
    "filename": "TDS 40.aseprite",
    "frame": { "x": 5120, "y": 0, "w": 128, "h": 128 },
    "rotated": false,
    "trimmed": false,
    "spriteSourceSize": { "x": 0, "y": 0, "w": 128, "h": 128 },
    "sourceSize": { "w": 128, "h": 128 },
    "duration": 20
   },
   {
    "filename": "TDS 41.aseprite",
    "frame": { "x": 5248, "y": 0, "w": 128, "h": 128 },
    "rotated": false,
    "trimmed": false,
    "spriteSourceSize": { "x": 0, "y": 0, "w": 128, "h": 128 },
    "sourceSize": { "w": 128, "h": 128 },
    "duration": 20
   },
   {
    "filename": "TDS 42.aseprite",
    "frame": { "x": 5376, "y": 0, "w": 128, "h": 128 },
    "rotated": false,
    "trimmed": false,
    "spriteSourceSize": { "x": 0, "y": 0, "w": 128, "h": 128 },
    "sourceSize": { "w": 128, "h": 128 },
    "duration": 20
   },
   {
    "filename": "TDS 43.aseprite",
    "frame": { "x": 5504, "y": 0, "w": 128, "h": 128 },
    "rotated": false,
    "trimmed": false,
    "spriteSourceSize": { "x": 0, "y": 0, "w": 128, "h": 128 },
    "sourceSize": { "w": 128, "h": 128 },
    "duration": 20
   },
   {
    "filename": "TDS 44.aseprite",
    "frame": { "x": 5632, "y": 0, "w": 128, "h": 128 },
    "rotated": false,
    "trimmed": false,
    "spriteSourceSize": { "x": 0, "y": 0, "w": 128, "h": 128 },
    "sourceSize": { "w": 128, "h": 128 },
    "duration": 20
   },
   {
    "filename": "TDS 45.aseprite",
    "frame": { "x": 5760, "y": 0, "w": 128, "h": 128 },
    "rotated": false,
    "trimmed": false,
    "spriteSourceSize": { "x": 0, "y": 0, "w": 128, "h": 128 },
    "sourceSize": { "w": 128, "h": 128 },
    "duration": 20
   },
   {
    "filename": "TDS 46.aseprite",
    "frame": { "x": 5888, "y": 0, "w": 128, "h": 128 },
    "rotated": false,
    "trimmed": false,
    "spriteSourceSize": { "x": 0, "y": 0, "w": 128, "h": 128 },
    "sourceSize": { "w": 128, "h": 128 },
    "duration": 20
   },
   {
    "filename": "TDS 47.aseprite",
    "frame": { "x": 6016, "y": 0, "w": 128, "h": 128 },
    "rotated": false,
    "trimmed": false,
    "spriteSourceSize": { "x": 0, "y": 0, "w": 128, "h": 128 },
    "sourceSize": { "w": 128, "h": 128 },
    "duration": 20
   },
   {
    "filename": "TDS 48.aseprite",
    "frame": { "x": 6144, "y": 0, "w": 128, "h": 128 },
    "rotated": false,
    "trimmed": false,
    "spriteSourceSize": { "x": 0, "y": 0, "w": 128, "h": 128 },
    "sourceSize": { "w": 128, "h": 128 },
    "duration": 20
   },
   {
    "filename": "TDS 49.aseprite",
    "frame": { "x": 6272, "y": 0, "w": 128, "h": 128 },
    "rotated": false,
    "trimmed": false,
    "spriteSourceSize": { "x": 0, "y": 0, "w": 128, "h": 128 },
    "sourceSize": { "w": 128, "h": 128 },
    "duration": 20
   },
   {
    "filename": "TDS 50.aseprite",
    "frame": { "x": 6400, "y": 0, "w": 128, "h": 128 },
    "rotated": false,
    "trimmed": false,
    "spriteSourceSize": { "x": 0, "y": 0, "w": 128, "h": 128 },
    "sourceSize": { "w": 128, "h": 128 },
    "duration": 20
   },
   {
    "filename": "TDS 51.aseprite",
    "frame": { "x": 6528, "y": 0, "w": 128, "h": 128 },
    "rotated": false,
    "trimmed": false,
    "spriteSourceSize": { "x": 0, "y": 0, "w": 128, "h": 128 },
    "sourceSize": { "w": 128, "h": 128 },
    "duration": 20
   },
   {
    "filename": "TDS 52.aseprite",
    "frame": { "x": 6656, "y": 0, "w": 128, "h": 128 },
    "rotated": false,
    "trimmed": false,
    "spriteSourceSize": { "x": 0, "y": 0, "w": 128, "h": 128 },
    "sourceSize": { "w": 128, "h": 128 },
    "duration": 20
   },
   {
    "filename": "TDS 53.aseprite",
    "frame": { "x": 6784, "y": 0, "w": 128, "h": 128 },
    "rotated": false,
    "trimmed": false,
    "spriteSourceSize": { "x": 0, "y": 0, "w": 128, "h": 128 },
    "sourceSize": { "w": 128, "h": 128 },
    "duration": 20
   },
   {
    "filename": "TDS 54.aseprite",
    "frame": { "x": 6912, "y": 0, "w": 128, "h": 128 },
    "rotated": false,
    "trimmed": false,
    "spriteSourceSize": { "x": 0, "y": 0, "w": 128, "h": 128 },
    "sourceSize": { "w": 128, "h": 128 },
    "duration": 20
   },
   {
    "filename": "TDS 55.aseprite",
    "frame": { "x": 7040, "y": 0, "w": 128, "h": 128 },
    "rotated": false,
    "trimmed": false,
    "spriteSourceSize": { "x": 0, "y": 0, "w": 128, "h": 128 },
    "sourceSize": { "w": 128, "h": 128 },
    "duration": 20
   },
   {
    "filename": "TDS 56.aseprite",
    "frame": { "x": 7168, "y": 0, "w": 128, "h": 128 },
    "rotated": false,
    "trimmed": false,
    "spriteSourceSize": { "x": 0, "y": 0, "w": 128, "h": 128 },
    "sourceSize": { "w": 128, "h": 128 },
    "duration": 20
   },
   {
    "filename": "TDS 57.aseprite",
    "frame": { "x": 7296, "y": 0, "w": 128, "h": 128 },
    "rotated": false,
    "trimmed": false,
    "spriteSourceSize": { "x": 0, "y": 0, "w": 128, "h": 128 },
    "sourceSize": { "w": 128, "h": 128 },
    "duration": 20
   },
   {
    "filename": "TDS 58.aseprite",
    "frame": { "x": 7424, "y": 0, "w": 128, "h": 128 },
    "rotated": false,
    "trimmed": false,
    "spriteSourceSize": { "x": 0, "y": 0, "w": 128, "h": 128 },
    "sourceSize": { "w": 128, "h": 128 },
    "duration": 20
   },
   {
    "filename": "TDS 59.aseprite",
    "frame": { "x": 7552, "y": 0, "w": 128, "h": 128 },
    "rotated": false,
    "trimmed": false,
    "spriteSourceSize": { "x": 0, "y": 0, "w": 128, "h": 128 },
    "sourceSize": { "w": 128, "h": 128 },
    "duration": 20
   },
   {
    "filename": "TDS 60.aseprite",
    "frame": { "x": 7680, "y": 0, "w": 128, "h": 128 },
    "rotated": false,
    "trimmed": false,
    "spriteSourceSize": { "x": 0, "y": 0, "w": 128, "h": 128 },
    "sourceSize": { "w": 128, "h": 128 },
    "duration": 20
   },
   {
    "filename": "TDS 61.aseprite",
    "frame": { "x": 7808, "y": 0, "w": 128, "h": 128 },
    "rotated": false,
    "trimmed": false,
    "spriteSourceSize": { "x": 0, "y": 0, "w": 128, "h": 128 },
    "sourceSize": { "w": 128, "h": 128 },
    "duration": 20
   },
   {
    "filename": "TDS 62.aseprite",
    "frame": { "x": 7936, "y": 0, "w": 128, "h": 128 },
    "rotated": false,
    "trimmed": false,
    "spriteSourceSize": { "x": 0, "y": 0, "w": 128, "h": 128 },
    "sourceSize": { "w": 128, "h": 128 },
    "duration": 20
   },
   {
    "filename": "TDS 63.aseprite",
    "frame": { "x": 8064, "y": 0, "w": 128, "h": 128 },
    "rotated": false,
    "trimmed": false,
    "spriteSourceSize": { "x": 0, "y": 0, "w": 128, "h": 128 },
    "sourceSize": { "w": 128, "h": 128 },
    "duration": 20
   },
   {
    "filename": "TDS 64.aseprite",
    "frame": { "x": 8192, "y": 0, "w": 128, "h": 128 },
    "rotated": false,
    "trimmed": false,
    "spriteSourceSize": { "x": 0, "y": 0, "w": 128, "h": 128 },
    "sourceSize": { "w": 128, "h": 128 },
    "duration": 20
   },
   {
    "filename": "TDS 65.aseprite",
    "frame": { "x": 8320, "y": 0, "w": 128, "h": 128 },
    "rotated": false,
    "trimmed": false,
    "spriteSourceSize": { "x": 0, "y": 0, "w": 128, "h": 128 },
    "sourceSize": { "w": 128, "h": 128 },
    "duration": 20
   },
   {
    "filename": "TDS 66.aseprite",
    "frame": { "x": 8448, "y": 0, "w": 128, "h": 128 },
    "rotated": false,
    "trimmed": false,
    "spriteSourceSize": { "x": 0, "y": 0, "w": 128, "h": 128 },
    "sourceSize": { "w": 128, "h": 128 },
    "duration": 20
   },
   {
    "filename": "TDS 67.aseprite",
    "frame": { "x": 8576, "y": 0, "w": 128, "h": 128 },
    "rotated": false,
    "trimmed": false,
    "spriteSourceSize": { "x": 0, "y": 0, "w": 128, "h": 128 },
    "sourceSize": { "w": 128, "h": 128 },
    "duration": 20
   },
   {
    "filename": "TDS 68.aseprite",
    "frame": { "x": 8704, "y": 0, "w": 128, "h": 128 },
    "rotated": false,
    "trimmed": false,
    "spriteSourceSize": { "x": 0, "y": 0, "w": 128, "h": 128 },
    "sourceSize": { "w": 128, "h": 128 },
    "duration": 20
   },
   {
    "filename": "TDS 69.aseprite",
    "frame": { "x": 8832, "y": 0, "w": 128, "h": 128 },
    "rotated": false,
    "trimmed": false,
    "spriteSourceSize": { "x": 0, "y": 0, "w": 128, "h": 128 },
    "sourceSize": { "w": 128, "h": 128 },
    "duration": 20
   },
   {
    "filename": "TDS 70.aseprite",
    "frame": { "x": 8960, "y": 0, "w": 128, "h": 128 },
    "rotated": false,
    "trimmed": false,
    "spriteSourceSize": { "x": 0, "y": 0, "w": 128, "h": 128 },
    "sourceSize": { "w": 128, "h": 128 },
    "duration": 20
   },
   {
    "filename": "TDS 71.aseprite",
    "frame": { "x": 9088, "y": 0, "w": 128, "h": 128 },
    "rotated": false,
    "trimmed": false,
    "spriteSourceSize": { "x": 0, "y": 0, "w": 128, "h": 128 },
    "sourceSize": { "w": 128, "h": 128 },
    "duration": 20
   },
   {
    "filename": "TDS 72.aseprite",
    "frame": { "x": 9216, "y": 0, "w": 128, "h": 128 },
    "rotated": false,
    "trimmed": false,
    "spriteSourceSize": { "x": 0, "y": 0, "w": 128, "h": 128 },
    "sourceSize": { "w": 128, "h": 128 },
    "duration": 20
   },
   {
    "filename": "TDS 73.aseprite",
    "frame": { "x": 9344, "y": 0, "w": 128, "h": 128 },
    "rotated": false,
    "trimmed": false,
    "spriteSourceSize": { "x": 0, "y": 0, "w": 128, "h": 128 },
    "sourceSize": { "w": 128, "h": 128 },
    "duration": 20
   },
   {
    "filename": "TDS 74.aseprite",
    "frame": { "x": 9472, "y": 0, "w": 128, "h": 128 },
    "rotated": false,
    "trimmed": false,
    "spriteSourceSize": { "x": 0, "y": 0, "w": 128, "h": 128 },
    "sourceSize": { "w": 128, "h": 128 },
    "duration": 20
   },
   {
    "filename": "TDS 75.aseprite",
    "frame": { "x": 9600, "y": 0, "w": 128, "h": 128 },
    "rotated": false,
    "trimmed": false,
    "spriteSourceSize": { "x": 0, "y": 0, "w": 128, "h": 128 },
    "sourceSize": { "w": 128, "h": 128 },
    "duration": 20
   },
   {
    "filename": "TDS 76.aseprite",
    "frame": { "x": 9728, "y": 0, "w": 128, "h": 128 },
    "rotated": false,
    "trimmed": false,
    "spriteSourceSize": { "x": 0, "y": 0, "w": 128, "h": 128 },
    "sourceSize": { "w": 128, "h": 128 },
    "duration": 20
   },
   {
    "filename": "TDS 77.aseprite",
    "frame": { "x": 9856, "y": 0, "w": 128, "h": 128 },
    "rotated": false,
    "trimmed": false,
    "spriteSourceSize": { "x": 0, "y": 0, "w": 128, "h": 128 },
    "sourceSize": { "w": 128, "h": 128 },
    "duration": 20
   },
   {
    "filename": "TDS 78.aseprite",
    "frame": { "x": 9984, "y": 0, "w": 128, "h": 128 },
    "rotated": false,
    "trimmed": false,
    "spriteSourceSize": { "x": 0, "y": 0, "w": 128, "h": 128 },
    "sourceSize": { "w": 128, "h": 128 },
    "duration": 20
   },
   {
    "filename": "TDS 79.aseprite",
    "frame": { "x": 10112, "y": 0, "w": 128, "h": 128 },
    "rotated": false,
    "trimmed": false,
    "spriteSourceSize": { "x": 0, "y": 0, "w": 128, "h": 128 },
    "sourceSize": { "w": 128, "h": 128 },
    "duration": 20
   }
 ],
 "meta": {
  "app": "https://www.aseprite.org/",
  "version": "1.2.30",
  "image": "TDS.png",
  "format": "I8",
  "size": { "w": 10240, "h": 128 },
  "scale": "1",
  "frameTags": [
  ],
  "layers": [
   { "name": "Layer", "opacity": 255, "blendMode": "normal" }
  ],
  "slices": [
  ]
 }
}
